{"nodes": [{"id": "f_agnishiksha_backend_src_controllers_student_home_controller_ts", "label": "home.controller.ts", "file_type": "code", "source_file": "F:\\AgniShiksha\\backend\\src\\controllers\\student\\home.controller.ts", "source_location": "L1"}, {"id": "home_controller_fetchwithversionedcache", "label": "fetchWithVersionedCache()", "file_type": "code", "source_file": "F:\\AgniShiksha\\backend\\src\\controllers\\student\\home.controller.ts", "source_location": "L7"}, {"id": "home_controller_gethomedashboard", "label": "getHomeDashboard()", "file_type": "code", "source_file": "F:\\AgniShiksha\\backend\\src\\controllers\\student\\home.controller.ts", "source_location": "L30"}], "edges": [{"source": "f_agnishiksha_backend_src_controllers_student_home_controller_ts", "target": "express", "relation": "imports_from", "confidence": "EXTRACTED", "source_file": "F:\\AgniShiksha\\backend\\src\\controllers\\student\\home.controller.ts", "source_location": "L3", "weight": 1.0}, {"source": "f_agnishiksha_backend_src_controllers_student_home_controller_ts", "target": "f_agnishiksha_backend_src_config_db", "relation": "imports_from", "confidence": "EXTRACTED", "source_file": "F:\\AgniShiksha\\backend\\src\\controllers\\student\\home.controller.ts", "source_location": "L4", "weight": 1.0}, {"source": "f_agnishiksha_backend_src_controllers_student_home_controller_ts", "target": "f_agnishiksha_backend_src_services_cache_service", "relation": "imports_from", "confidence": "EXTRACTED", "source_file": "F:\\AgniShiksha\\backend\\src\\controllers\\student\\home.controller.ts", "source_location": "L5", "weight": 1.0}, {"source": "f_agnishiksha_backend_src_controllers_student_home_controller_ts", "target": "home_controller_fetchwithversionedcache", "relation": "contains", "confidence": "EXTRACTED", "source_file": "F:\\AgniShiksha\\backend\\src\\controllers\\student\\home.controller.ts", "source_location": "L7", "weight": 1.0}, {"source": "f_agnishiksha_backend_src_controllers_student_home_controller_ts", "target": "home_controller_gethomedashboard", "relation": "contains", "confidence": "EXTRACTED", "source_file": "F:\\AgniShiksha\\backend\\src\\controllers\\student\\home.controller.ts", "source_location": "L30", "weight": 1.0}, {"source": "home_controller_gethomedashboard", "target": "home_controller_fetchwithversionedcache", "relation": "calls", "confidence": "EXTRACTED", "source_file": "F:\\AgniShiksha\\backend\\src\\controllers\\student\\home.controller.ts", "source_location": "L132", "weight": 1.0}], "raw_calls": [{"caller_nid": "home_controller_fetchwithversionedcache", "callee": "await CacheService.get", "source_file": "F:\\AgniShiksha\\backend\\src\\controllers\\student\\home.controller.ts", "source_location": "L16"}, {"caller_nid": "home_controller_fetchwithversionedcache", "callee": "fetcher", "source_file": "F:\\AgniShiksha\\backend\\src\\controllers\\student\\home.controller.ts", "source_location": "L20"}, {"caller_nid": "home_controller_fetchwithversionedcache", "callee": "set", "source_file": "F:\\AgniShiksha\\backend\\src\\controllers\\student\\home.controller.ts", "source_location": "L21"}, {"caller_nid": "home_controller_fetchwithversionedcache", "callee": "error", "source_file": "F:\\AgniShiksha\\backend\\src\\controllers\\student\\home.controller.ts", "source_location": "L24"}, {"caller_nid": "home_controller_fetchwithversionedcache", "callee": "fetcher", "source_file": "F:\\AgniShiksha\\backend\\src\\controllers\\student\\home.controller.ts", "source_location": "L26"}, {"caller_nid": "home_controller_gethomedashboard", "callee": "now", "source_file": "F:\\AgniShiksha\\backend\\src\\controllers\\student\\home.controller.ts", "source_location": "L32"}, {"caller_nid": "home_controller_gethomedashboard", "callee": "findUnique", "source_file": "F:\\AgniShiksha\\backend\\src\\controllers\\student\\home.controller.ts", "source_location": "L37"}, {"caller_nid": "home_controller_gethomedashboard", "callee": "json", "source_file": "F:\\AgniShiksha\\backend\\src\\controllers\\student\\home.controller.ts", "source_location": "L59"}, {"caller_nid": "home_controller_gethomedashboard", "callee": "status", "source_file": "F:\\AgniShiksha\\backend\\src\\controllers\\student\\home.controller.ts", "source_location": "L59"}, {"caller_nid": "home_controller_gethomedashboard", "callee": "substring", "source_file": "F:\\AgniShiksha\\backend\\src\\controllers\\student\\home.controller.ts", "source_location": "L66"}, {"caller_nid": "home_controller_gethomedashboard", "callee": "toISOString", "source_file": "F:\\AgniShiksha\\backend\\src\\controllers\\student\\home.controller.ts", "source_location": "L66"}, {"caller_nid": "home_controller_gethomedashboard", "callee": "substring", "source_file": "F:\\AgniShiksha\\backend\\src\\controllers\\student\\home.controller.ts", "source_location": "L68"}, {"caller_nid": "home_controller_gethomedashboard", "callee": "toISOString", "source_file": "F:\\AgniShiksha\\backend\\src\\controllers\\student\\home.controller.ts", "source_location": "L68"}, {"caller_nid": "home_controller_gethomedashboard", "callee": "abs", "source_file": "F:\\AgniShiksha\\backend\\src\\controllers\\student\\home.controller.ts", "source_location": "L84"}, {"caller_nid": "home_controller_gethomedashboard", "callee": "getTime", "source_file": "F:\\AgniShiksha\\backend\\src\\controllers\\student\\home.controller.ts", "source_location": "L84"}, {"caller_nid": "home_controller_gethomedashboard", "callee": "getTime", "source_file": "F:\\AgniShiksha\\backend\\src\\controllers\\student\\home.controller.ts", "source_location": "L84"}, {"caller_nid": "home_controller_gethomedashboard", "callee": "round", "source_file": "F:\\AgniShiksha\\backend\\src\\controllers\\student\\home.controller.ts", "source_location": "L85"}, {"caller_nid": "home_controller_gethomedashboard", "callee": "setImmediate", "source_file": "F:\\AgniShiksha\\backend\\src\\controllers\\student\\home.controller.ts", "source_location": "L104"}, {"caller_nid": "home_controller_gethomedashboard", "callee": "now", "source_file": "F:\\AgniShiksha\\backend\\src\\controllers\\student\\home.controller.ts", "source_location": "L120"}, {"caller_nid": "home_controller_gethomedashboard", "callee": "all", "source_file": "F:\\AgniShiksha\\backend\\src\\controllers\\student\\home.controller.ts", "source_location": "L130"}, {"caller_nid": "home_controller_gethomedashboard", "callee": "now", "source_file": "F:\\AgniShiksha\\backend\\src\\controllers\\student\\home.controller.ts", "source_location": "L190"}, {"caller_nid": "home_controller_gethomedashboard", "callee": "json", "source_file": "F:\\AgniShiksha\\backend\\src\\controllers\\student\\home.controller.ts", "source_location": "L193"}, {"caller_nid": "home_controller_gethomedashboard", "callee": "status", "source_file": "F:\\AgniShiksha\\backend\\src\\controllers\\student\\home.controller.ts", "source_location": "L193"}, {"caller_nid": "home_controller_gethomedashboard", "callee": "toFixed", "source_file": "F:\\AgniShiksha\\backend\\src\\controllers\\student\\home.controller.ts", "source_location": "L196"}, {"caller_nid": "home_controller_gethomedashboard", "callee": "toFixed", "source_file": "F:\\AgniShiksha\\backend\\src\\controllers\\student\\home.controller.ts", "source_location": "L197"}, {"caller_nid": "home_controller_gethomedashboard", "callee": "toFixed", "source_file": "F:\\AgniShiksha\\backend\\src\\controllers\\student\\home.controller.ts", "source_location": "L198"}, {"caller_nid": "home_controller_gethomedashboard", "callee": "error", "source_file": "F:\\AgniShiksha\\backend\\src\\controllers\\student\\home.controller.ts", "source_location": "L221"}, {"caller_nid": "home_controller_gethomedashboard", "callee": "json", "source_file": "F:\\AgniShiksha\\backend\\src\\controllers\\student\\home.controller.ts", "source_location": "L222"}, {"caller_nid": "home_controller_gethomedashboard", "callee": "status", "source_file": "F:\\AgniShiksha\\backend\\src\\controllers\\student\\home.controller.ts", "source_location": "L222"}]}